cernservicexml/__init__.py
cernservicexml/_compat.py
cernservicexml/document.py
cernservicexml/publisher.py
cernservicexml/version.py
cernservicexml-0.2.1.dist-info/DESCRIPTION.rst
cernservicexml-0.2.1.dist-info/METADATA
cernservicexml-0.2.1.dist-info/metadata.json
cernservicexml-0.2.1.dist-info/pbr.json
cernservicexml-0.2.1.dist-info/RECORD
cernservicexml-0.2.1.dist-info/top_level.txt
cernservicexml-0.2.1.dist-info/WHEEL
