Metadata-Version: 2.0
Name: cernservicexml
Version: 0.2.1
Summary: Small library to generate a CERN XSLS Service XML.
Home-page: https://github.com/inveniosoftware/cernservicexml
Author: Invenio Collaboration
Author-email: info@invenio-software.org
License: UNKNOWN
Platform: UNKNOWN
Classifier: Programming Language :: Python :: 2
Classifier: Programming Language :: Python :: 2.6
Classifier: Programming Language :: Python :: 2.7
Classifier: Programming Language :: Python :: 3
Classifier: Programming Language :: Python :: 3.3
Classifier: Programming Language :: Python :: 3.4
Classifier: Development Status :: 5 - Production/Stable
Classifier: Intended Audience :: Developers
Classifier: License :: OSI Approved :: BSD License
Classifier: Operating System :: OS Independent
Classifier: Topic :: Utilities
Requires-Dist: requests (>=1.1.0)
Provides-Extra: docs
Requires-Dist: sphinx-rtd-theme; extra == 'docs'
